{"cameraMode":{"drawMode":0,"name":"Shaded","section":"Shading Mode"},"sceneLighting":true,"audioPlay":false,"sceneViewState":{"showFog":true,"showMaterialUpdate":false,"showSkybox":true,"showFlares":true,"showImageEffects":true,"showParticleSystems":true},"in2DMode":false,"pivot":{"x":2.531116485595703,"y":-2.413479804992676,"z":58.024662017822269},"rotation":{"x":-0.13538165390491486,"y":0.4225684106349945,"z":-0.0639958456158638,"w":-0.8938822150230408},"size":88.02269744873047,"orthographic":false}